musketeer/__init__.py
musketeer/__main__.py
musketeer/contributingSpecies.py
musketeer/contributors.py
musketeer/editData.py
musketeer/equilibriumConstants.py
musketeer/fitSignals.py
musketeer/knownSignals.py
musketeer/logo 16px.png
musketeer/logo 48px.png
musketeer/logo 512px.png
musketeer/logo macos 1024px.png
musketeer/moduleFrame.py
musketeer/patchMatplotlib.py
musketeer/progressDialog.py
musketeer/proportionality.py
musketeer/scrolledFrame.py
musketeer/speciation.py
musketeer/style.py
musketeer/table.py
musketeer/titration.py
musketeer/titrationFrame.py
musketeer/titrationReader.py
musketeer/totalConcentrations.py
musketeer/windowsHighDpiPatch.py
musketeer-1.10.1.dist-info/LICENSE
musketeer-1.10.1.dist-info/METADATA
musketeer-1.10.1.dist-info/WHEEL
musketeer-1.10.1.dist-info/top_level.txt
musketeer-1.10.1.dist-info/RECORD
